mappie/__init__.py
mappie/py.typed
mappie-0.1.0.dist-info/LICENSE
mappie-0.1.0.dist-info/WHEEL
mappie-0.1.0.dist-info/METADATA
mappie-0.1.0.dist-info/RECORD
